easycli/__init__.py
easycli/argument.py
easycli/colors.py
easycli/command.py
easycli/completion.py
easycli/progressbar.py
easycli/root.py
easycli-1.0.0.dist-info/LICENSE
easycli-1.0.0.dist-info/METADATA
easycli-1.0.0.dist-info/WHEEL
easycli-1.0.0.dist-info/top_level.txt
easycli-1.0.0.dist-info/RECORD
